Datacenter_leo_client.py
setup.py
Datacenter_leo_client.egg-info/PKG-INFO
Datacenter_leo_client.egg-info/SOURCES.txt
Datacenter_leo_client.egg-info/dependency_links.txt
Datacenter_leo_client.egg-info/requires.txt
Datacenter_leo_client.egg-info/top_level.txt