Metadata-Version: 2.1
Name: Datacenter-leo-client
Version: 0.1
Summary: A package for managing the datacenter
Author: LEONARDO Germany GmbH
Author-email: N.Dulal@leonardogermany.com
